{
  "source": "clinicaltrials",
  "query": {
    "drug": "Latanoprost",
    "disease": "primary hereditary glaucoma"
  },
  "data": [
    {
      "registry": "ClinicalTrials.gov",
      "id": "NCT01527682",
      "title": "Efficacy and Safety of Prostaglandin Analogue and Carbonic Anhydrase Inhibitor for the Treatment of Pediatric Glaucoma",
      "phase": "PHASE2",
      "status": "COMPLETED",
      "start_date": "2009-07",
      "completion_date": "2016-11",
      "country": "Italy",
      "enrollment": 37,
      "brief_summary": "Objectives:\n\nThe study will assess the ocular hypotensive effect of latanoprost and dorzolamide in a selected sample of patients affected by primary Pediatric Glaucoma (PG), refractory to surgical procedures. Safety will be assessed, too.In the first version of the protocol 96 eyes were forecasted to complete the enrolment. The protocol was then amended and now to complete the study 68 eyes should be included. This number of eyes could be achieved by recruiting from 34 to 68 patients due to not ",
      "eligibility_criteria": "Inclusion Criteria:\n\n* Children of either sexes, aged 0-12 years\n* Diagnosis of mono- or bilateral primary congenital glaucoma\n* IOP greater than or equal to 22 mmHg and lower than 27 mmHg\n* Only one previous ocular hypotensive surgical procedure for treatment of glaucoma among the following: goniot",
      "endpoints": [
        "Percentage of Eyes With Response"
      ],
      "sponsor": "Azienda Socio Sanitaria Territoriale degli Spedali Civili di Brescia",
      "url": "https://clinicaltrials.gov/study/NCT01527682"
    }
  ],
  "timestamp": "2026-03-10T12:24:33.842744",
  "success": true,
  "error_message": null
}