{
  "source": "tctr",
  "query": {
    "drug": "Azithromycin",
    "disease": "hyperamylasemia",
    "search_query": "Azithromycin hyperamylasemia"
  },
  "data": {
    "drug": "Azithromycin",
    "disease": "hyperamylasemia",
    "trials": [],
    "count": 0,
    "source": "Thai Clinical Trial Registry",
    "search_url": "https://www.thaiclinicaltrials.org/show/search?q=Azithromycin%20hyperamylasemia"
  },
  "timestamp": "2026-03-10T13:07:55.413719",
  "success": true,
  "error_message": null
}