{
  "source": "tctr",
  "query": {
    "drug": "Cyclosporine",
    "disease": "prolapse of lacrimal gland",
    "search_query": "Cyclosporine prolapse of lacrimal gland"
  },
  "data": {
    "drug": "Cyclosporine",
    "disease": "prolapse of lacrimal gland",
    "trials": [],
    "count": 0,
    "source": "Thai Clinical Trial Registry",
    "search_url": "https://www.thaiclinicaltrials.org/show/search?q=Cyclosporine%20prolapse%20of%20lacrimal%20gland"
  },
  "timestamp": "2026-03-10T13:33:25.899245",
  "success": true,
  "error_message": null
}