{
  "source": "tctr",
  "query": {
    "drug": "Magnesium sulfate",
    "disease": "psychotic disorder",
    "search_query": "Magnesium sulfate psychotic disorder"
  },
  "data": {
    "drug": "Magnesium sulfate",
    "disease": "psychotic disorder",
    "trials": [],
    "count": 0,
    "source": "Thai Clinical Trial Registry",
    "search_url": "https://www.thaiclinicaltrials.org/show/search?q=Magnesium%20sulfate%20psychotic%20disorder"
  },
  "timestamp": "2026-03-10T13:00:39.173230",
  "success": true,
  "error_message": null
}