{
  "source": "tctr",
  "query": {
    "drug": "Phenytoin",
    "disease": "audiogenic seizures",
    "search_query": "Phenytoin audiogenic seizures"
  },
  "data": {
    "drug": "Phenytoin",
    "disease": "audiogenic seizures",
    "trials": [],
    "count": 0,
    "source": "Thai Clinical Trial Registry",
    "search_url": "https://www.thaiclinicaltrials.org/show/search?q=Phenytoin%20audiogenic%20seizures"
  },
  "timestamp": "2026-03-10T12:18:29.798283",
  "success": true,
  "error_message": null
}