{
  "source": "tctr",
  "query": {
    "drug": "Pioglitazone",
    "disease": "centrifugal lipodystrophy",
    "search_query": "Pioglitazone centrifugal lipodystrophy"
  },
  "data": {
    "drug": "Pioglitazone",
    "disease": "centrifugal lipodystrophy",
    "trials": [],
    "count": 0,
    "source": "Thai Clinical Trial Registry",
    "search_url": "https://www.thaiclinicaltrials.org/show/search?q=Pioglitazone%20centrifugal%20lipodystrophy"
  },
  "timestamp": "2026-03-10T13:52:26.845223",
  "success": true,
  "error_message": null
}