{
  "source": "tctr",
  "query": {
    "drug": "Pravastatin",
    "disease": "homozygous familial hypercholesterolemia",
    "search_query": "Pravastatin homozygous familial hypercholesterolemia"
  },
  "data": {
    "drug": "Pravastatin",
    "disease": "homozygous familial hypercholesterolemia",
    "trials": [],
    "count": 0,
    "source": "Thai Clinical Trial Registry",
    "search_url": "https://www.thaiclinicaltrials.org/show/search?q=Pravastatin%20homozygous%20familial%20hypercholesterolemia"
  },
  "timestamp": "2026-03-10T13:37:28.378545",
  "success": true,
  "error_message": null
}