{
  "source": "tctr",
  "query": {
    "drug": "Simvastatin",
    "disease": "familial hypercholesterolemia",
    "search_query": "Simvastatin familial hypercholesterolemia"
  },
  "data": {
    "drug": "Simvastatin",
    "disease": "familial hypercholesterolemia",
    "trials": [],
    "count": 0,
    "source": "Thai Clinical Trial Registry",
    "search_url": "https://www.thaiclinicaltrials.org/show/search?q=Simvastatin%20familial%20hypercholesterolemia"
  },
  "timestamp": "2026-03-10T13:02:35.382495",
  "success": true,
  "error_message": null
}