{
  "source": "tctr",
  "query": {
    "drug": "Simvastatin",
    "disease": "hypercholesterolemia, autosomal dominant",
    "search_query": "Simvastatin hypercholesterolemia, autosomal dominant"
  },
  "data": {
    "drug": "Simvastatin",
    "disease": "hypercholesterolemia, autosomal dominant",
    "trials": [],
    "count": 0,
    "source": "Thai Clinical Trial Registry",
    "search_url": "https://www.thaiclinicaltrials.org/show/search?q=Simvastatin%20hypercholesterolemia%2C%20autosomal%20dominant"
  },
  "timestamp": "2026-03-10T13:03:15.904604",
  "success": true,
  "error_message": null
}